awslabs/__init__.py
awslabs/cdk_mcp_server/__init__.py
awslabs/cdk_mcp_server/server.py
awslabs/cdk_mcp_server/core/__init__.py
awslabs/cdk_mcp_server/core/resources.py
awslabs/cdk_mcp_server/core/search_utils.py
awslabs/cdk_mcp_server/core/server.py
awslabs/cdk_mcp_server/core/tools.py
awslabs/cdk_mcp_server/data/__init__.py
awslabs/cdk_mcp_server/data/cdk_nag_parser.py
awslabs/cdk_mcp_server/data/construct_descriptions.py
awslabs/cdk_mcp_server/data/genai_cdk_loader.py
awslabs/cdk_mcp_server/data/lambda_layer_parser.py
awslabs/cdk_mcp_server/data/lambda_powertools_loader.py
awslabs/cdk_mcp_server/data/schema_generator.py
awslabs/cdk_mcp_server/data/solutions_constructs_parser.py
awslabs/cdk_mcp_server/static/__init__.py
mseep_awslabs_cdk_mcp_server-1.0.3.dist-info/licenses/LICENSE
mseep_awslabs_cdk_mcp_server-1.0.3.dist-info/licenses/NOTICE
tests/__init__.py
mseep_awslabs_cdk_mcp_server-1.0.3.dist-info/METADATA
mseep_awslabs_cdk_mcp_server-1.0.3.dist-info/WHEEL
mseep_awslabs_cdk_mcp_server-1.0.3.dist-info/top_level.txt
mseep_awslabs_cdk_mcp_server-1.0.3.dist-info/RECORD
