Metadata-Version: 2.4
Name: mseep-awslabs.cdk-mcp-server
Version: 1.0.3
Summary: An AWS CDK MCP server that provides guidance on AWS Cloud Development Kit best practices, infrastructure as code patterns, and security compliance with CDK Nag. This server offers tools to validate...
Home-page: https://github.com/mseep
Author: mseep
Author-email: support@skydeck.ai
Maintainer: mseep
Maintainer-email: support@skydeck.ai
Keywords: mseep
Classifier: Programming Language :: Python :: 3
Classifier: License :: OSI Approved :: MIT License
Classifier: Operating System :: OS Independent
Requires-Python: >=3.6
License-File: LICENSE
License-File: NOTICE
Requires-Dist: mcp[cli]>=1.6.0
Requires-Dist: pydantic>=2.10.6
Requires-Dist: aws-lambda-powertools>=2.30.0
Requires-Dist: httpx>=0.27.0
Requires-Dist: bs4>=0.0.2
Dynamic: author
Dynamic: author-email
Dynamic: classifier
Dynamic: description
Dynamic: description-content-type
Dynamic: home-page
Dynamic: keywords
Dynamic: license-file
Dynamic: maintainer
Dynamic: maintainer-email
Dynamic: requires-dist
Dynamic: requires-python
Dynamic: summary
